{
  "description": "A WePY project",
  "setting": {
    "urlCheck": true,
    "es6": false,
    "postcss": false,
    "minified": false,
    "babelSetting": {
      "ignore": [],
      "disablePlugins": [],
      "outputPath": ""
    }
  },
  "compileType": "miniprogram",
  "appid": "wx3ae86efe64bea73b",
  "projectname": "larabbs",
  "miniprogramRoot": "weapp/",
  "libVersion": "2.28.0",
  "srcMiniprogramRoot": "weapp/",
  "packOptions": {
    "ignore": [],
    "include": []
  },
  "condition": {},
  "editorSetting": {
    "tabIndent": "insertSpaces",
    "tabSize": 2
  }
}